eefpy/__init__.py
eefpy/solver/__init__.py
eefpy/solver/eef.py
eefpy/solver/solver.py
eefpy/solver_cpp/Makefile
eefpy/solver_cpp/config.cpp
eefpy/solver_cpp/config.h
eefpy/solver_cpp/cplex.cpp
eefpy/solver_cpp/cplex.h
eefpy/solver_cpp/eef.cpp
eefpy/solver_cpp/eef.h
eefpy/solver_cpp/main.cpp
eefpy/solver_cpp/sample_config
eefpy/solver_cpp/stats.cpp
eefpy/solver_cpp/trading_cycle.cpp
eefpy/solver_cpp/trading_cycle.h
eefpy/solver_cpp/ilp_model/model.cpp
eefpy/solver_cpp/ilp_model/model.h
eefpy/solver_cpp/ilp_model/primary.cpp
eefpy/solver_cpp/ilp_model/primary.h
eefpy/solver_cpp/ilp_model/efficiency/efficiency.cpp
eefpy/solver_cpp/ilp_model/efficiency/efficiency.h
eefpy/solver_cpp/ilp_model/efficiency/mintc.cpp
eefpy/solver_cpp/ilp_model/efficiency/mintc.h
eefpy/solver_cpp/ilp_model/efficiency/none.cpp
eefpy/solver_cpp/ilp_model/efficiency/none.h
eefpy/solver_cpp/ilp_model/efficiency/pareto.cpp
eefpy/solver_cpp/ilp_model/efficiency/pareto.h
eefpy-0.1.5.dist-info/COPYING
eefpy-0.1.5.dist-info/LICENSE
eefpy-0.1.5.dist-info/METADATA
eefpy-0.1.5.dist-info/WHEEL
eefpy-0.1.5.dist-info/top_level.txt
eefpy-0.1.5.dist-info/RECORD
