Metadata-Version: 2.1
Name: eefpy
Version: 0.1.5
Summary: python eef practical solver
Home-page: https://github.com/ariel-research/eefpy
Author-email: ariel-research <eefpy@csariel.xyz>
Maintainer-email: eefpy Developers <eefpy-discuss@googlegroups.com>
License: GNU GENERAL PUBLIC LICENSE
Project-URL: Source Code, https://github.com/ariel-research/eefpy
Keywords: Fair Allocation,Mathematics
Requires-Python: >=3.8
License-File: LICENSE
License-File: COPYING
Requires-Dist: cppyy
